pubtools/_pulp/__init__.py
pubtools/_pulp/arguments.py
pubtools/_pulp/hooks.py
pubtools/_pulp/step.py
pubtools/_pulp/task.py
pubtools/_pulp/ud.py
pubtools/_pulp/services/__init__.py
pubtools/_pulp/services/base.py
pubtools/_pulp/services/cachingpulp.py
pubtools/_pulp/services/collector.py
pubtools/_pulp/services/fakepulp.py
pubtools/_pulp/services/pulp.py
pubtools/_pulp/services/udcache.py
pubtools/_pulp/tasks/__init__.py
pubtools/_pulp/tasks/clear_repo.py
pubtools/_pulp/tasks/common.py
pubtools/_pulp/tasks/copy_repo.py
pubtools/_pulp/tasks/delete.py
pubtools/_pulp/tasks/fix_cves.py
pubtools/_pulp/tasks/garbage_collect.py
pubtools/_pulp/tasks/publish.py
pubtools/_pulp/tasks/push/__init__.py
pubtools/_pulp/tasks/push/command.py
pubtools/_pulp/tasks/push/contextlib_compat.py
pubtools/_pulp/tasks/push/copy.py
pubtools/_pulp/tasks/push/items/__init__.py
pubtools/_pulp/tasks/push/items/base.py
pubtools/_pulp/tasks/push/items/comps.py
pubtools/_pulp/tasks/push/items/direct.py
pubtools/_pulp/tasks/push/items/erratum.py
pubtools/_pulp/tasks/push/items/erratum_conv.py
pubtools/_pulp/tasks/push/items/file.py
pubtools/_pulp/tasks/push/items/modulemd.py
pubtools/_pulp/tasks/push/items/productid.py
pubtools/_pulp/tasks/push/items/rpm.py
pubtools/_pulp/tasks/push/phase/__init__.py
pubtools/_pulp/tasks/push/phase/associate.py
pubtools/_pulp/tasks/push/phase/base.py
pubtools/_pulp/tasks/push/phase/buffer.py
pubtools/_pulp/tasks/push/phase/collect.py
pubtools/_pulp/tasks/push/phase/constants.py
pubtools/_pulp/tasks/push/phase/context.py
pubtools/_pulp/tasks/push/phase/end_push.py
pubtools/_pulp/tasks/push/phase/errors.py
pubtools/_pulp/tasks/push/phase/load_items.py
pubtools/_pulp/tasks/push/phase/load_sums.py
pubtools/_pulp/tasks/push/phase/progress.py
pubtools/_pulp/tasks/push/phase/publish.py
pubtools/_pulp/tasks/push/phase/push_post_actions.py
pubtools/_pulp/tasks/push/phase/query_pulp.py
pubtools/_pulp/tasks/push/phase/update.py
pubtools/_pulp/tasks/push/phase/upload.py
pubtools_pulp-1.33.2.dist-info/LICENSE
pubtools_pulp-1.33.2.dist-info/METADATA
pubtools_pulp-1.33.2.dist-info/WHEEL
pubtools_pulp-1.33.2.dist-info/entry_points.txt
pubtools_pulp-1.33.2.dist-info/top_level.txt
pubtools_pulp-1.33.2.dist-info/RECORD
