Metadata-Version: 2.1
Name: pubtools-pulp
Version: 1.33.2
Summary: Publishing tools for Pulp
Home-page: https://github.com/release-engineering/pubtools-pulp
License: GNU General Public License
Project-URL: Documentation, https://release-engineering.github.io/pubtools-pulp/
Project-URL: Changelog, https://github.com/release-engineering/pubtools-pulp/blob/master/CHANGELOG.md
Platform: UNKNOWN
Classifier: Development Status :: 4 - Beta
Classifier: Intended Audience :: Developers
Classifier: License :: OSI Approved :: GNU General Public License v3 or later (GPLv3+)
Classifier: Programming Language :: Python :: 3
Classifier: Topic :: Software Development :: Libraries :: Python Modules
Requires-Python: >=3.6
Requires-Dist: pubtools>=0.3.0
Requires-Dist: pubtools-pulplib>=2.36.0
Requires-Dist: more-executors>=2.7.0
Requires-Dist: pushcollector>=1.2.0
Requires-Dist: pushsource>=2.51.0
Requires-Dist: monotonic; python_version < "3.3"
